[
  {
    "canonical": "葉哲泰",
    "type": "person",
    "aliases": ["葉文潔的父親", "葉文潔父親"],
    "related_terms": ["批判大會", "紅衛兵", "四個女孩兒", "施暴", "奪去父親生命", "父親已沒有生命的軀體", "遺體"],
    "triggers": [
      {"all": ["葉文潔", "父親"]},
      {"all": ["葉文潔", "爸爸"]}
    ]
  },
  {
    "canonical": "申玉菲",
    "type": "person",
    "aliases": ["日籍華裔物理學家"],
    "related_terms": ["技術研討會", "通過她", "認識了幾位物理專業的朋友", "科學邊界成員"],
    "triggers": [
      {"all": ["汪淼", "科學邊界"]},
      {"all": ["最初", "科學邊界"]},
      {"all": ["誰", "介紹", "科學邊界"]}
    ]
  },
  {
    "canonical": "納米材料",
    "type": "concept",
    "aliases": ["奈米材料", "納米技術", "奈米技術", "納米構件"],
    "related_terms": ["新材料", "中華二號", "高能加速器", "納米構件部分"],
    "triggers": [
      {"all": ["汪淼", "研究"]},
      {"all": ["汪淼", "前沿技術"]},
      {"all": ["汪淼", "從事"]}
    ]
  },
  {
    "canonical": "亂紀元與恆紀元",
    "type": "concept",
    "aliases": ["亂紀元", "恆紀元", "恒紀元"],
    "related_terms": ["三顆太陽", "三體運動", "行星圍繞", "穩定運行", "引力範圍", "游移不定"],
    "triggers": [
      {"all": ["亂紀元", "恆紀元"]},
      {"all": ["亂紀元", "恒紀元"]}
    ]
  },
  {
    "canonical": "智子",
    "type": "concept",
    "aliases": ["智子工程", "質子計算機"],
    "related_terms": ["干擾加速器", "三台加速器", "基礎科學", "神跡計劃", "實時監視", "實時通訊"],
    "triggers": [
      {"all": ["智子", "任務"]},
      {"all": ["智子", "主要"]},
      {"all": ["智子", "影響", "基礎科學"]}
    ]
  },
  {
    "canonical": "地球三體組織",
    "type": "organization",
    "aliases": ["ETO", "地球三體叛軍", "三體組織", "地球三體運動"],
    "related_terms": ["降臨派", "拯救派", "倖存派", "精神領袖", "三體叛軍", "主", "毀滅人類文明", "幫助三體文明", "利用和製造環境問題", "製造環境災難"],
    "triggers": [
      {"all": ["ETO"]},
      {"all": ["地球三體組織"]},
      {"all": ["三體組織"]},
      {"all": ["地球三體組織", "目的"]},
      {"all": ["ETO", "目的"]}
    ]
  },
  {
    "canonical": "三顆太陽",
    "type": "concept",
    "aliases": ["三個太陽", "三日連珠", "三日凌空"],
    "related_terms": ["三體運動", "半人馬座三星", "飛星", "恆星系統"],
    "triggers": [
      {"all": ["三體文明", "太陽"]},
      {"all": ["恆星系統", "幾顆太陽"]}
    ]
  },
  {
    "canonical": "科學家自殺事件",
    "type": "event",
    "aliases": ["科學家自殺", "頂尖科學家自殺", "學者自殺", "多位科學家接連自殺", "學者接連自殺"],
    "related_terms": ["楊冬", "丁儀", "遺書", "物理學從來就沒有存在過", "物理學不存在", "三台新的高能加速器", "實驗結果", "沒有規律", "科學邊界", "智子", "干擾加速器", "錯誤的撞擊結果", "基礎科學", "科學信念崩塌"],
    "triggers": [
      {"all": ["科學家", "自殺"]},
      {"all": ["學者", "自殺"]},
      {"all": ["頂尖", "科學家", "自殺"]},
      {"all": ["接連", "自殺"]}
    ]
  },
  {
    "canonical": "物理學不存在了",
    "type": "event",
    "aliases": ["物理學不存在", "物理學從來就沒有存在過", "物理學將來也不會存在"],
    "related_terms": ["楊冬", "丁儀", "遺書", "一切的一切都導向這樣一個結果", "三台新的高能加速器", "實驗結果", "沒有規律", "科學邊界", "現代物理學", "基礎科學"],
    "triggers": [
      {"all": ["物理學", "不存在"]},
      {"all": ["物理學不存在了"]},
      {"all": ["物理學從來", "存在"]}
    ]
  },
  {
    "canonical": "葉文潔回覆三體文明",
    "type": "event",
    "aliases": ["紅岸基地重要決定", "影響人類命運的重要決定", "再次發送訊號", "回覆三體文明", "向宇宙發送訊號", "按下發射鍵"],
    "related_terms": ["葉文潔", "紅岸基地", "紅岸之六", "發射系統", "天線定位器", "太陽", "發射鍵", "毫不猶豫", "正在飛向太陽的信息", "到這裏來吧", "我將幫助你們獲得這個世界", "我的文明已無力解決自己的問題", "需要你們的力量來介入"],
    "triggers": [
      {"all": ["葉文潔", "紅岸", "重要決定"]},
      {"all": ["葉文潔", "影響人類命運"]},
      {"all": ["葉文潔", "紅岸基地", "決定"]},
      {"all": ["葉文潔", "做出", "決定"]}
    ]
  },
  {
    "canonical": "不要回答警告",
    "type": "event",
    "aliases": ["第一次收到外星文明回覆", "外星文明回覆", "對方警告", "不要回答"],
    "related_terms": ["葉文潔", "紅岸", "監聽員", "警告信息", "不要回答！不要回答！不要回答", "這個世界收到了你們的信息", "發射源將被定位", "無法定位發射源", "你們的行星系將遭到入侵", "你們的世界將被佔領", "坐標", "佔領", "入侵", "征服"],
    "triggers": [
      {"all": ["第一次", "收到", "回覆"]},
      {"all": ["外星文明", "警告"]},
      {"all": ["對方", "警告"]},
      {"all": ["葉文潔", "警告"]},
      {"all": ["不要回答"]}
    ]
  },
  {
    "canonical": "葉文潔人生經歷",
    "type": "character_arc",
    "aliases": ["葉文潔的人生經歷", "葉文潔後來的選擇", "人生經歷影響選擇", "對人類失望", "人類惡的一面"],
    "related_terms": ["葉哲泰", "父親", "父親慘死", "文化大革命", "紅衛兵", "寂靜的春天", "人類惡的一面", "不可愈合的巨創", "理性的思考", "白沐霖", "背叛", "1969年", "監室", "程麗華", "紅岸基地", "不要回答", "到這裏來吧", "我將幫助你們獲得這個世界", "我的文明已無力解決自己的問題"],
    "triggers": [
      {"all": ["葉文潔", "人生經歷"]},
      {"all": ["葉文潔", "後來", "選擇"]},
      {"all": ["葉文潔", "失望"]},
      {"all": ["葉文潔", "影響", "選擇"]}
    ]
  },
  {
    "canonical": "葉文潔紅岸時期",
    "type": "timeline",
    "aliases": ["調往紅岸基地", "進入紅岸基地", "紅岸基地工作時期", "被調往紅岸"],
    "related_terms": ["1969年", "文革", "文化大革命", "建設兵團", "大興安嶺", "程麗華", "軍代表", "監室", "基地的工作人員", "再也不能離開", "紅岸工程", "紅岸工程第147次發射", "寒冷的星空"],
    "triggers": [
      {"all": ["葉文潔", "紅岸基地", "時期"]},
      {"all": ["葉文潔", "調往", "紅岸"]},
      {"all": ["葉文潔", "紅岸基地", "工作"]},
      {"all": ["葉文潔", "被調往"]}
    ]
  },
  {
    "canonical": "人類文明弱點",
    "type": "theme",
    "aliases": ["人類文明的弱點", "人類弱點", "文明弱點", "人類文明問題"],
    "related_terms": ["葉哲泰", "父親慘死", "文化大革命", "紅衛兵", "白沐霖", "背叛", "寂靜的春天", "人類惡的一面", "地球三體組織", "世界屬於三體", "毀滅全人類", "降臨派", "紅岸回覆", "到這裏來吧", "古箏行動", "人類社會已經不可能依靠自身的力量"],
    "triggers": [
      {"all": ["人類文明", "弱點"]},
      {"all": ["哪些事件", "弱點"]},
      {"all": ["最能體現", "人類文明"]},
      {"all": ["人類", "弱點"]}
    ]
  },
  {
    "canonical": "三體文明生存問題",
    "type": "concept",
    "aliases": ["三體文明根本生存問題", "三體世界生存問題", "三體根本問題"],
    "related_terms": ["三顆太陽", "三個太陽", "亂紀元", "恆紀元", "三體運動", "三體問題", "不可解", "沒有規律", "半人馬座"],
    "triggers": [
      {"all": ["三體文明", "生存問題"]},
      {"all": ["三體文明", "根本"]},
      {"all": ["三體世界", "生存"]}
    ]
  },
  {
    "canonical": "三體訊號接收",
    "type": "event",
    "aliases": ["三體文明收到地球訊號", "三體文明收到地球信號", "監聽員收到訊號"],
    "related_terms": ["1379號監聽站", "監聽員", "聆聽", "智慧文明的信息", "第一次讀到了來自另一個世界的信息", "這個世界收到了你們的信息"],
    "triggers": [
      {"all": ["三體文明", "收到", "地球"]},
      {"all": ["三體文明", "訊號"]},
      {"all": ["三體文明", "信號"]}
    ]
  },
  {
    "canonical": "三體世界距離",
    "type": "fact",
    "aliases": ["三體世界距離地球", "三體文明距離地球", "三體星系距離地球"],
    "related_terms": ["四光年", "四光年左右", "半人馬座三星", "距地球", "最近的恆星系"],
    "triggers": [
      {"all": ["三體世界", "距離", "地球"]},
      {"all": ["三體世界", "多遠"]},
      {"all": ["三體文明", "幾光年"]}
    ]
  },
  {
    "canonical": "紅岸基地官方目的",
    "type": "fact",
    "aliases": ["紅岸基地最初建立目的", "紅岸工程官方目的", "紅岸工程建立目的"],
    "related_terms": ["國防科研基地", "紅岸工程", "尋找外星文明", "外星文明探索", "搜索監聽", "信息發送", "監聽敵人航天器", "射電天文"],
    "triggers": [
      {"all": ["紅岸基地", "官方目的"]},
      {"all": ["紅岸基地", "最初建立"]},
      {"all": ["紅岸工程", "目的"]}
    ]
  },
  {
    "canonical": "伊文斯與葉文潔相識",
    "type": "event",
    "aliases": ["麥克伊文斯與葉文潔相識", "伊文斯和葉文潔認識", "伊文斯初遇葉文潔"],
    "related_terms": ["伊文斯", "麥克", "葉文潔", "大興安嶺", "樹林", "砍樹", "父親", "遺產", "物種共產主義"],
    "triggers": [
      {"all": ["伊文斯", "葉文潔", "相識"]},
      {"all": ["伊文斯", "葉文潔", "認識"]},
      {"all": ["麥克", "葉文潔", "情況"]}
    ]
  },
  {
    "canonical": "三體遊戲預測方法",
    "type": "concept",
    "aliases": ["三體遊戲預測太陽方法", "預測太陽運動規律的方法", "三體文明預測太陽運動"],
    "related_terms": ["周文王", "墨子", "模擬宇宙", "人列計算機", "馮。諾伊曼", "馮。諾依曼", "牛頓", "秦始皇", "數值法", "微分方程", "預測太陽"],
    "triggers": [
      {"all": ["遊戲", "預測", "太陽"]},
      {"all": ["三體", "哪些方法"]},
      {"all": ["太陽運動", "方法"]}
    ]
  },
  {
    "canonical": "三體遊戲歷史人物",
    "type": "concept",
    "aliases": ["三體遊戲人物", "三體問題歷史人物", "遊戲中歷史人物"],
    "related_terms": ["周文王", "墨子", "孔子", "秦始皇", "牛頓", "馮。諾伊曼", "馮。諾依曼", "哥白尼", "伽利略", "愛因斯坦", "開普勒", "赫歇爾"],
    "triggers": [
      {"all": ["遊戲", "歷史人物"]},
      {"all": ["遊戲", "哪些人物"]},
      {"all": ["三體問題", "人物"]}
    ]
  },
  {
    "canonical": "三體艦隊前往地球原因",
    "type": "event",
    "aliases": ["三體文明派遣艦隊", "三體艦隊前往地球", "三體文明決定前往地球"],
    "related_terms": ["地球文明回電", "三體艦隊", "航向這顆恆星", "距離最近", "生存空間", "技術水平", "加速發展", "遏制地球文明的科學發展"],
    "triggers": [
      {"all": ["三體文明", "艦隊", "地球"]},
      {"all": ["三體文明", "派遣", "艦隊"]},
      {"all": ["三體文明", "前往地球"]}
    ]
  },
  {
    "canonical": "汪淼倒數計時呈現方式",
    "type": "event",
    "aliases": ["汪淼倒計時", "幽靈倒計時", "倒數計時數字"],
    "related_terms": ["照片", "底片", "膠片", "一排數字", "相機", "眼睛", "視野", "視網膜", "智子"],
    "triggers": [
      {"all": ["汪淼", "倒數計時"]},
      {"all": ["汪淼", "倒計時"]},
      {"all": ["倒數", "數字", "呈現"]}
    ]
  },
  {
    "canonical": "常偉思角色",
    "type": "person",
    "aliases": ["常將軍", "常偉思將軍"],
    "related_terms": ["軍方", "作戰中心", "首長", "科學邊界", "大史", "軍警合作", "調查"],
    "triggers": [
      {"all": ["常偉思", "職務"]},
      {"all": ["常偉思", "角色"]},
      {"all": ["常偉思", "身分"]}
    ]
  },
  {
    "canonical": "ETO合理觀點",
    "type": "theme",
    "aliases": ["ETO成員合理之處", "地球三體組織合理想法", "ETO想法合理之處"],
    "related_terms": ["人類文明徹底絕望", "降臨派", "拯救派", "倖存派", "環境", "物種大滅絕", "人類社會", "拯救主", "三體問題", "人類自我修正"],
    "triggers": [
      {"all": ["ETO", "合理"]},
      {"all": ["ETO", "想法"]},
      {"all": ["地球三體組織", "合理"]}
    ]
  }
]
